nexp/__init__.py
nexp/config.py
nexp/launcher.py
nexp/parser.py
nexp/trainer.py
nexp/utils.py
nexp/datasets/__init__.py
nexp/datasets/datastats.py
nexp/datasets/loader.py
nexp/frameworks/__init__.py
nexp/frameworks/cifar.py
nexp/frameworks/ssl.py
nexp/frameworks/ssl_sup.py
nexp/models/__init__.py
nexp/models/vision.py
nexp-0.0.1.dist-info/LICENSE.txt
nexp-0.0.1.dist-info/METADATA
nexp-0.0.1.dist-info/WHEEL
nexp-0.0.1.dist-info/top_level.txt
nexp-0.0.1.dist-info/RECORD
