Metadata-Version: 2.1
Name: nexp
Version: 0.0.1
Summary: Research library to try out deep learning ideas easily.
Author-email: Vivien Cabannes <vivien.cabannes@gmail.com>
Project-URL: Homepage, https://github.com:VivienCabannes/nexp
Project-URL: Bug Tracker, https://github.com/VivienCabannes/nexp/issues
Classifier: Programming Language :: Python :: 3
Classifier: License :: OSI Approved :: MIT License
Classifier: Operating System :: OS Independent
Requires-Python: >=3.10
License-File: LICENSE.txt
